stream_tool/Websockets_Auth.py
stream_tool/__init__.py
stream_tool/_button.py
stream_tool/_core.py
stream_tool/_create_obs_websocket_manager.py
stream_tool/_create_website.py
stream_tool/_data.py
stream_tool/_formatting_and_converting.py
stream_tool/_page.py
stream_tool/_website.py
stream_tool/builtin_obs_actions.py
stream_tool/exceptions.py
stream_tool/resources/static/light-bulb.png
stream_tool/resources/templates/404.html
stream_tool/resources/templates/page_template.html
stream_tool-0.1.0.dist-info/LICENSE
stream_tool-0.1.0.dist-info/METADATA
stream_tool-0.1.0.dist-info/WHEEL
stream_tool-0.1.0.dist-info/RECORD
