Metadata-Version: 2.1
Name: stream-tool
Version: 0.1.0
Summary: a simple tool for making macros
Home-page: https://github.com/pyskyler/stream-tool
License: MIT
Author: skylerficklin
Author-email: skylerficklin@gmail.com
Requires-Python: >=3.10,<4.0
Classifier: License :: OSI Approved :: MIT License
Classifier: Programming Language :: Python :: 3
Classifier: Programming Language :: Python :: 3.10
Classifier: Programming Language :: Python :: 3.11
Classifier: Programming Language :: Python :: 3.12
Requires-Dist: Flask (>=3.0.0,<4.0.0)
Requires-Dist: obs-websocket-py (>=1.0,<2.0)
Project-URL: Documentation, https://stream-tool.readthedocs.io
Project-URL: Repository, https://github.com/pyskyler/stream-tool
